NiuKeyunYinggangQiuzhiJingyanFenxiang20212022Fix1/README.md
NiuKeyunYinggangQiuzhiJingyanFenxiang20212022Fix1/__init__.py
NiuKeyunYinggangQiuzhiJingyanFenxiang20212022Fix1/__main__.py
NiuKeyunYinggangQiuzhiJingyanFenxiang20212022Fix1/file.epub
NiuKeyunYinggangQiuzhiJingyanFenxiang20212022Fix1/index.html
NiuKeyunYinggangQiuzhiJingyanFenxiang20212022Fix1/css/__init__.py
NiuKeyunYinggangQiuzhiJingyanFenxiang20212022Fix1/css/annotations.css
NiuKeyunYinggangQiuzhiJingyanFenxiang20212022Fix1/css/main.css
NiuKeyunYinggangQiuzhiJingyanFenxiang20212022Fix1/css/normalize.css
NiuKeyunYinggangQiuzhiJingyanFenxiang20212022Fix1/css/popup.css
NiuKeyunYinggangQiuzhiJingyanFenxiang20212022Fix1/font/__init__.py
NiuKeyunYinggangQiuzhiJingyanFenxiang20212022Fix1/font/fontello.eot
NiuKeyunYinggangQiuzhiJingyanFenxiang20212022Fix1/font/fontello.svg
NiuKeyunYinggangQiuzhiJingyanFenxiang20212022Fix1/font/fontello.ttf
NiuKeyunYinggangQiuzhiJingyanFenxiang20212022Fix1/font/fontello.woff
NiuKeyunYinggangQiuzhiJingyanFenxiang20212022Fix1/img/__init__.py
NiuKeyunYinggangQiuzhiJingyanFenxiang20212022Fix1/img/annotator-glyph-sprite.png
NiuKeyunYinggangQiuzhiJingyanFenxiang20212022Fix1/img/annotator-icon-sprite.png
NiuKeyunYinggangQiuzhiJingyanFenxiang20212022Fix1/img/apple-touch-icon.png
NiuKeyunYinggangQiuzhiJingyanFenxiang20212022Fix1/img/cancelfullscreen.png
NiuKeyunYinggangQiuzhiJingyanFenxiang20212022Fix1/img/close.png
NiuKeyunYinggangQiuzhiJingyanFenxiang20212022Fix1/img/fullscreen.png
NiuKeyunYinggangQiuzhiJingyanFenxiang20212022Fix1/img/loader.gif
NiuKeyunYinggangQiuzhiJingyanFenxiang20212022Fix1/img/menu-icon.png
NiuKeyunYinggangQiuzhiJingyanFenxiang20212022Fix1/img/save.png
NiuKeyunYinggangQiuzhiJingyanFenxiang20212022Fix1/img/saved.png
NiuKeyunYinggangQiuzhiJingyanFenxiang20212022Fix1/img/settings-s.png
NiuKeyunYinggangQiuzhiJingyanFenxiang20212022Fix1/img/settings.png
NiuKeyunYinggangQiuzhiJingyanFenxiang20212022Fix1/img/star.png
niu_keyun_yinggang_qiuzhi_jingyan_fenxiang_2021_2022_fix1-2025.3.25.0.dist-info/METADATA
niu_keyun_yinggang_qiuzhi_jingyan_fenxiang_2021_2022_fix1-2025.3.25.0.dist-info/WHEEL
niu_keyun_yinggang_qiuzhi_jingyan_fenxiang_2021_2022_fix1-2025.3.25.0.dist-info/entry_points.txt
niu_keyun_yinggang_qiuzhi_jingyan_fenxiang_2021_2022_fix1-2025.3.25.0.dist-info/top_level.txt
niu_keyun_yinggang_qiuzhi_jingyan_fenxiang_2021_2022_fix1-2025.3.25.0.dist-info/RECORD
